LinkExpander/__init__.py
LinkExpander/linktypes.py
LinkExpander/main.py
LinkExpander-1.1.0.dist-info/METADATA
LinkExpander-1.1.0.dist-info/WHEEL
LinkExpander-1.1.0.dist-info/top_level.txt
LinkExpander-1.1.0.dist-info/RECORD
