Metadata-Version: 2.1
Name: LinkExpander
Version: 1.1.0
Summary: Link expander in Python which parses and returns the URLs and information in common link domains.
Author-email: devdagoat <fidevran@hotmail.com>
Project-URL: Homepage, https://github.com/devdagoat/LinkExpander
Classifier: Programming Language :: Python :: 3
Classifier: License :: OSI Approved :: MIT License
Classifier: Operating System :: OS Independent
Requires-Python: >=3.10
